MANIFEST.in
README.txt
setup.cfg
setup.py
atreal/__init__.py
atreal/__init__.pyc
atreal.cmfeditions.unlocker.egg-info/PKG-INFO
atreal.cmfeditions.unlocker.egg-info/SOURCES.txt
atreal.cmfeditions.unlocker.egg-info/dependency_links.txt
atreal.cmfeditions.unlocker.egg-info/entry_points.txt
atreal.cmfeditions.unlocker.egg-info/namespace_packages.txt
atreal.cmfeditions.unlocker.egg-info/not-zip-safe
atreal.cmfeditions.unlocker.egg-info/requires.txt
atreal.cmfeditions.unlocker.egg-info/top_level.txt
atreal/cmfeditions/__init__.py
atreal/cmfeditions/__init__.pyc
atreal/cmfeditions/unlocker/UnlockerModifier.py
atreal/cmfeditions/unlocker/UnlockerModifier.pyc
atreal/cmfeditions/unlocker/__init__.py
atreal/cmfeditions/unlocker/__init__.pyc
atreal/cmfeditions/unlocker/configure.zcml
atreal/cmfeditions/unlocker/setuphandlers.py
atreal/cmfeditions/unlocker/setuphandlers.pyc
atreal/cmfeditions/unlocker/version.txt
atreal/cmfeditions/unlocker/profiles/default/metadata.xml
atreal/cmfeditions/unlocker/profiles/default/unlocker_various.txt
atreal/cmfeditions/unlocker/www/UnlockerModifier.pt
atreal/cmfeditions/unlocker/www/UnlockerModifierAddForm.pt
atreal/cmfeditions/unlocker/www/modifier.gif
docs/HISTORY.txt
docs/INSTALL.txt
docs/LICENSE.GPL
docs/LICENSE.txt