Metadata-Version: 1.0
Name: atreal.cmfeditions.unlocker
Version: 1.0.0
Summary: CMFEditions modifier that unlocks clone before saving
Home-page: http://www.atreal.net
Author: atReal
Author-email: contact@atreal.net
License: GPL
Keywords: plone cmfeditions zope atreal externaleditor webdav
Platform: UNKNOWN
Classifier: Framework :: Plone
Classifier: Programming Language :: Python
